literate_dataclasses.py
literate_dataclasses-0.0.6.dist-info/LICENSE
literate_dataclasses-0.0.6.dist-info/METADATA
literate_dataclasses-0.0.6.dist-info/WHEEL
literate_dataclasses-0.0.6.dist-info/top_level.txt
literate_dataclasses-0.0.6.dist-info/RECORD
