Metadata-Version: 2.1
Name: literate-dataclasses
Version: 0.0.6
Summary: A simple dataclasses wrapper for easier documentation of dataclasses
Home-page: https://github.com/stes/literate-dataclasses
Author: Steffen Schneider
Author-email: steffen@bethgelab.org
Project-URL: Bug Tracker, https://github.com/stes/literate-dataclasses/issues
Classifier: Programming Language :: Python :: 3
Classifier: Intended Audience :: Developers
Classifier: License :: OSI Approved :: MIT License
Classifier: Topic :: Software Development :: Libraries
Classifier: Topic :: Utilities
Requires-Python: >=3.8
License-File: LICENSE
Provides-Extra: install_requires
Requires-Dist: pytest ; extra == 'install_requires'
